worldmaster/__init__.py
worldmaster/admin.py
worldmaster/apps.py
worldmaster/asgi.py
worldmaster/models.py
worldmaster/urls.py
worldmaster/validators.py
worldmaster/wsgi.py
worldmaster/migrations/0001_initial.py
worldmaster/migrations/__init__.py
worldmaster/settings/__init__.py
worldmaster/settings/development.py
worldmaster-0.1.0.dist-info/WHEEL
worldmaster-0.1.0.dist-info/METADATA
worldmaster-0.1.0.dist-info/RECORD
